LICENSE
MANIFEST.in
README.rst
setup.py
examples/conkyrc.example
pywu/__init__.py
pywu/pywu.py
pywu.egg-info/PKG-INFO
pywu.egg-info/SOURCES.txt
pywu.egg-info/dependency_links.txt
pywu.egg-info/entry_points.txt
pywu.egg-info/top_level.txt