Metadata-Version: 1.1
Name: pywu
Version: 1.1
Summary: A simple python script for fetching data from Weather Underground's API.
Home-page: https://github.com/dh4/pywu
Author: Dan Hasting
Author-email: dan@hasting.info
License: BSD
Platform: UNKNOWN
Classifier: Development Status :: 5 - Production/Stable
Classifier: Environment :: Console
Classifier: Intended Audience :: End Users/Desktop
Classifier: Operating System :: POSIX
Classifier: License :: OSI Approved :: BSD License
Classifier: Natural Language :: English
Classifier: Programming Language :: Python
Classifier: Programming Language :: Python :: 3.3
Classifier: Programming Language :: Python :: 3.4
